wakumo_ai/__init__.py
wakumo_ai/api/__init__.py
wakumo_ai/api/conversation.py
wakumo_ai/api/file.py
wakumo_ai/cli.py
wakumo_ai/client.py
wakumo_ai/commands/__init__.py
wakumo_ai/commands/conversation.py
wakumo_ai/config.py
wakumo_ai/log.py
wakumo_ai/models/__init__.py
wakumo_ai/models/conversation.py
wakumo_ai/ws/__init__.py
wakumo_ai/ws/base.py
wakumo_ai-0.1.2.dist-info/METADATA
wakumo_ai-0.1.2.dist-info/WHEEL
wakumo_ai-0.1.2.dist-info/entry_points.txt
wakumo_ai-0.1.2.dist-info/RECORD
